webstack/__init__.py
webstack/admin.py
webstack/apps.py
webstack/models.py
webstack/tests.py
webstack/urls.py
webstack/views.py
webstack/migrations/0001_initial.py
webstack/migrations/0002_auto_20230724_1835.py
webstack/migrations/0003_auto_20230725_1401.py
webstack/migrations/__init__.py
webstack/static/webstack/assets/css/nav.css
webstack/static/webstack/assets/css/xenon-components.css
webstack/static/webstack/assets/css/xenon-core.css
webstack/static/webstack/assets/css/xenon-forms.css
webstack/static/webstack/assets/css/xenon-skins.css
webstack/static/webstack/assets/css/xenon.css
webstack/static/webstack/assets/images/favicon.png
webstack/static/webstack/assets/images/logo-collapsed@2x.png
webstack/static/webstack/assets/images/logo@2x.png
webstack/static/webstack/assets/images/preview.gif
webstack/static/webstack/assets/js/TweenMax.min.js
webstack/static/webstack/assets/js/joinable.js
webstack/static/webstack/assets/js/lozad.js
webstack/static/webstack/assets/js/resizeable.js
webstack/static/webstack/assets/js/xenon-api.js
webstack/static/webstack/assets/js/xenon-custom.js
webstack/static/webstack/assets/js/xenon-toggles.js
webstack/templates/webstack/base.html
webstack/templates/webstack/index.html
django_webstack-1.5.4.dist-info/LICENSE
django_webstack-1.5.4.dist-info/METADATA
django_webstack-1.5.4.dist-info/WHEEL
django_webstack-1.5.4.dist-info/top_level.txt
django_webstack-1.5.4.dist-info/RECORD
