Metadata-Version: 2.1
Name: django-webstack
Version: 1.5.4
Summary: webstack of Django
Home-page: https://github.com/Hopetree/django-webstack
Author: Hopetree
Author-email: zlwork2014@163.com
Keywords: django webstack navigation
Classifier: Operating System :: OS Independent
Classifier: Intended Audience :: Developers
Classifier: License :: OSI Approved :: MIT License
Classifier: Programming Language :: Python
Classifier: Programming Language :: Python :: 3
Classifier: Programming Language :: Python :: 3.5
Classifier: Programming Language :: Python :: 3.6
Classifier: Programming Language :: Python :: 3.7
Classifier: Programming Language :: Python :: 3.8
Classifier: Framework :: Django
Classifier: Framework :: Django :: 1.8
Classifier: Framework :: Django :: 1.9
Classifier: Framework :: Django :: 1.10
Classifier: Framework :: Django :: 1.11
Classifier: Framework :: Django :: 2.0
Classifier: Framework :: Django :: 2.1
Classifier: Framework :: Django :: 2.2
Classifier: Framework :: Django :: 3.0
Requires-Python: >=3.5
License-File: LICENSE
Requires-Dist: Django (>=2.2)
Requires-Dist: Pillow (>=9.3.0)
Requires-Dist: django-imagekit (>=4.0.2)
